protobuf_distutils/__init__.py
protobuf_distutils/generate_py_protobufs.py
protobuf_distutils-1.0rc1.dist-info/METADATA
protobuf_distutils-1.0rc1.dist-info/WHEEL
protobuf_distutils-1.0rc1.dist-info/entry_points.txt
protobuf_distutils-1.0rc1.dist-info/top_level.txt
protobuf_distutils-1.0rc1.dist-info/RECORD
