Metadata-Version: 2.1
Name: protobuf-distutils
Version: 1.0rc1
Summary: This is a distutils extension to generate Python code for .proto files using an installed protoc binary.
Home-page: https://github.com/protocolbuffers/protobuf/
Maintainer: protobuf@googlegroups.com
Maintainer-email: protobuf@googlegroups.com
License: 3-Clause BSD License
Platform: UNKNOWN
Classifier: Framework :: Setuptools Plugin
Classifier: Operating System :: OS Independent
Classifier: Programming Language :: Python
Classifier: Programming Language :: Python :: 2
Classifier: Programming Language :: Python :: 2.7
Classifier: Programming Language :: Python :: 3
Classifier: Programming Language :: Python :: 3.3
Classifier: Programming Language :: Python :: 3.4
Classifier: Programming Language :: Python :: 3.5
Classifier: Programming Language :: Python :: 3.6
Classifier: Programming Language :: Python :: 3.7
Classifier: Programming Language :: Python :: 3.8
Classifier: Topic :: Software Development :: Code Generators
